telecli/__init__.py
telecli/test.py
telecli-0.0.1.dist-info/METADATA
telecli-0.0.1.dist-info/WHEEL
telecli-0.0.1.dist-info/top_level.txt
telecli-0.0.1.dist-info/RECORD
